AUTHORS.rst
CONTRIBUTING.rst
HISTORY.rst
LICENSE
MANIFEST.in
README.rst
setup.cfg
setup.py
docs/Makefile
docs/authors.rst
docs/conf.py
docs/contributing.rst
docs/history.rst
docs/index.rst
docs/installation.rst
docs/make.bat
docs/readme.rst
docs/usage.rst
sky_wiremock/__init__.py
sky_wiremock/sky_wiremock.py
sky_wiremock/utils.py
sky_wiremock.egg-info/PKG-INFO
sky_wiremock.egg-info/SOURCES.txt
sky_wiremock.egg-info/dependency_links.txt
sky_wiremock.egg-info/entry_points.txt
sky_wiremock.egg-info/not-zip-safe
sky_wiremock.egg-info/requires.txt
sky_wiremock.egg-info/top_level.txt
tests/test_methods.py
tests/mappings/epg.json
tests/mappings/epgEpisodeTitle.json