Metadata-Version: 2.1
Name: sky-wiremock
Version: 0.3.11
Summary: Python HTTP client for wiremock
Home-page: https://github.com/grubert65/sky_wiremock
Author: Marco Masetti
Author-email: marco.masetti@sky.uk
License: BSD license
Keywords: sky_wiremock
Platform: UNKNOWN
Classifier: Development Status :: 2 - Pre-Alpha
Classifier: Intended Audience :: Developers
Classifier: License :: OSI Approved :: BSD License
Classifier: Natural Language :: English
Classifier: Programming Language :: Python :: 2
Classifier: Programming Language :: Python :: 2.7
Classifier: Programming Language :: Python :: 3
Classifier: Programming Language :: Python :: 3.4
Classifier: Programming Language :: Python :: 3.5
Classifier: Programming Language :: Python :: 3.6
Classifier: Programming Language :: Python :: 3.7
License-File: LICENSE
License-File: AUTHORS.rst
